subject_classification_spanish/.DS_Store
subject_classification_spanish/__init__.py
subject_classification_spanish/subject_classifier.py
subject_classification_spanish/test_subject_classifier.py
subject_classification_spanish/__pycache__/cleaner.cpython-37.pyc
subject_classification_spanish/__pycache__/sentiment_analysis.cpython-37.pyc
subject_classification_spanish/__pycache__/subject_classifier.cpython-37.pyc
subject_classification_spanish/saved_model/model.h5
subject_classification_spanish/saved_model/model.json
subject_classification_spanish/saved_model/model_main_tags.h5
subject_classification_spanish/saved_model/model_main_tags.json
subject_classification_spanish/saved_model/multilabel_binarizer.pickle
subject_classification_spanish/saved_model/multilabel_binarizer_main_tags.pickle
subject_classification_spanish/saved_model/tokenizer.pickle
subject_classification_spanish/saved_model/tokenizer_main_tags.pickle
subject_classification_spanish-0.0.10.dist-info/LICENSE
subject_classification_spanish-0.0.10.dist-info/METADATA
subject_classification_spanish-0.0.10.dist-info/WHEEL
subject_classification_spanish-0.0.10.dist-info/top_level.txt
subject_classification_spanish-0.0.10.dist-info/RECORD
