Metadata-Version: 2.1
Name: subject-classification-spanish
Version: 0.0.10
Summary: Subject and topic analysis for sentences in spanish
Home-page: https://github.com/news-scrapers/subject-classification-spanish
Author: Hugo J. Bello
Author-email: hjbello.wk@gmail.com
License: UNKNOWN
Platform: UNKNOWN
Classifier: Programming Language :: Python :: 3
Classifier: License :: OSI Approved :: MIT License
Classifier: Operating System :: OS Independent
